LICENSE.md
README.md
setup.cfg
setup.py
metaron/__init__.py
metaron.egg-info/PKG-INFO
metaron.egg-info/SOURCES.txt
metaron.egg-info/dependency_links.txt
metaron.egg-info/requires.txt
metaron.egg-info/top_level.txt